nuscenes_hacker/__init__.py
nuscenes_hacker/main.py
nuscenes_hacker/hack/__init__.py
nuscenes_hacker/hack/hack.py
nuscenes_hacker/hack/main.py
nuscenes_hacker/restore/__init__.py
nuscenes_hacker/restore/main.py
nuscenes_hacker/tools/cli.py
nuscenes_hacker-0.0.8.dist-info/LICENSE
nuscenes_hacker-0.0.8.dist-info/METADATA
nuscenes_hacker-0.0.8.dist-info/WHEEL
nuscenes_hacker-0.0.8.dist-info/entry_points.txt
nuscenes_hacker-0.0.8.dist-info/top_level.txt
nuscenes_hacker-0.0.8.dist-info/RECORD
