Metadata-Version: 2.1
Name: nuscenes_hacker
Version: 0.0.8
Summary: nuscenes-hacker
Author-email: windzu <windzu1@gmail.com>
License: MIT
Keywords: nuscenes
Classifier: Development Status :: 3 - Alpha
Classifier: Intended Audience :: Developers
Classifier: License :: OSI Approved :: MIT License
Classifier: Natural Language :: English
Classifier: Programming Language :: Python :: 3
Requires-Python: <3.9,>=3.6
License-File: LICENSE
Requires-Dist: pyyaml
Requires-Dist: nuscenes-devkit
Requires-Dist: rich
Requires-Dist: typer
